Metadata-Version: 2.1
Name: bob.math
Version: 3.1.9
Summary: Mathematical functions of Bob
Home-page: https://gitlab.idiap.ch/bob/bob.math
Author: Andre Anjos
Author-email: andre.anjos@idiap.ch
License: BSD
Platform: UNKNOWN
Classifier: Framework :: Bob
Classifier: Development Status :: 4 - Beta
Classifier: Intended Audience :: Developers
Classifier: License :: OSI Approved :: BSD License
Classifier: Natural Language :: English
Classifier: Programming Language :: Python
Classifier: Programming Language :: Python :: 3
Classifier: Topic :: Software Development :: Libraries :: Python Modules
License-File: LICENSE
